{
  "scriptId": "673",
  "url": "file:///Users/loongallday/Library/Caches/deno/npm/registry.npmjs.org/@fast-csv/parse/4.3.6/build/src/parser/Parser.js",
  "functions": [
    {
      "functionName": "",
      "ranges": [
        {
          "startOffset": 0,
          "endOffset": 2835,
          "count": 1
        }
      ],
      "isBlockCoverage": true
    },
    {
      "functionName": "",
      "ranges": [
        {
          "startOffset": 1,
          "endOffset": 2834,
          "count": 1
        }
      ],
      "isBlockCoverage": true
    },
    {
      "functionName": "",
      "ranges": [
        {
          "startOffset": 214,
          "endOffset": 2828,
          "count": 1
        }
      ],
      "isBlockCoverage": true
    },
    {
      "functionName": "Parser",
      "ranges": [
        {
          "startOffset": 462,
          "endOffset": 612,
          "count": 0
        }
      ],
      "isBlockCoverage": false
    },
    {
      "functionName": "removeBOM",
      "ranges": [
        {
          "startOffset": 624,
          "endOffset": 889,
          "count": 0
        }
      ],
      "isBlockCoverage": false
    },
    {
      "functionName": "parse",
      "ranges": [
        {
          "startOffset": 894,
          "endOffset": 1264,
          "count": 0
        }
      ],
      "isBlockCoverage": false
    },
    {
      "functionName": "parseWithoutComments",
      "ranges": [
        {
          "startOffset": 1269,
          "endOffset": 1513,
          "count": 0
        }
      ],
      "isBlockCoverage": false
    },
    {
      "functionName": "parseWithComments",
      "ranges": [
        {
          "startOffset": 1518,
          "endOffset": 2331,
          "count": 0
        }
      ],
      "isBlockCoverage": false
    },
    {
      "functionName": "parseRow",
      "ranges": [
        {
          "startOffset": 2336,
          "endOffset": 2764,
          "count": 0
        }
      ],
      "isBlockCoverage": false
    }
  ]
}