{
  "scriptId": "337",
  "url": "file:///Users/loongallday/pdeservice-spb/supabase/functions/api-roles/handlers/search.ts",
  "functions": [
    {
      "functionName": "",
      "ranges": [
        {
          "startOffset": 0,
          "endOffset": 767,
          "count": 1
        }
      ],
      "isBlockCoverage": true
    },
    {
      "functionName": "search",
      "ranges": [
        {
          "startOffset": 290,
          "endOffset": 766,
          "count": 0
        }
      ],
      "isBlockCoverage": false
    }
  ]
}