{
  "scriptId": "724",
  "url": "file:///Users/loongallday/Library/Caches/deno/npm/registry.npmjs.org/compress-commons/4.1.2/lib/compress-commons.js",
  "functions": [
    {
      "functionName": "",
      "ranges": [
        {
          "startOffset": 0,
          "endOffset": 722,
          "count": 1
        }
      ],
      "isBlockCoverage": true
    },
    {
      "functionName": "",
      "ranges": [
        {
          "startOffset": 1,
          "endOffset": 721,
          "count": 1
        }
      ],
      "isBlockCoverage": true
    },
    {
      "functionName": "",
      "ranges": [
        {
          "startOffset": 214,
          "endOffset": 715,
          "count": 1
        }
      ],
      "isBlockCoverage": true
    }
  ]
}